<?xml version="1.0" encoding="utf-8"?><ViNoSaveData xmlns:xsd="http://www.w3.org/2001/XMLSchema" xmlns:xsi="http://www.w3.org/2001/XMLSchema-instance"><m_LoadedLevelIndex>1</m_LoadedLevelIndex><m_LoadedLevelName>Example Visual Novel</m_LoadedLevelName><m_CurrentScenarioName>DialogScene1</m_CurrentScenarioName><m_NodeName>DialogScene1/START/1_Dialog/ID_3</m_NodeName><m_SceneXmlData>﻿&lt;?xml version="1.0" encoding="utf-8"?&gt;&lt;SceneData xmlns:xsd="http://www.w3.org/2001/XMLSchema" xmlns:xsi="http://www.w3.org/2001/XMLSchema-instance"&gt;&lt;m_DataArray&gt;&lt;SceneNodeData&gt;&lt;name&gt;BG&lt;/name&gt;&lt;parentname&gt;ADVScene&lt;/parentname&gt;&lt;nodeType&gt;NODE&lt;/nodeType&gt;&lt;posX&gt;0&lt;/posX&gt;&lt;posY&gt;0&lt;/posY&gt;&lt;posZ&gt;2&lt;/posZ&gt;&lt;rotX&gt;-0&lt;/rotX&gt;&lt;rotY&gt;0&lt;/rotY&gt;&lt;rotZ&gt;0&lt;/rotZ&gt;&lt;sclX&gt;1&lt;/sclX&gt;&lt;sclY&gt;1&lt;/sclY&gt;&lt;sclZ&gt;1&lt;/sclZ&gt;&lt;uiAtlasName /&gt;&lt;texturePath /&gt;&lt;alpha&gt;1&lt;/alpha&gt;&lt;show&gt;true&lt;/show&gt;&lt;makePixelPerfect&gt;false&lt;/makePixelPerfect&gt;&lt;/SceneNodeData&gt;&lt;SceneNodeData&gt;&lt;name&gt;layer1&lt;/name&gt;&lt;parentname&gt;BG&lt;/parentname&gt;&lt;nodeType&gt;LEAF&lt;/nodeType&gt;&lt;posX&gt;0&lt;/posX&gt;&lt;posY&gt;0&lt;/posY&gt;&lt;posZ&gt;0&lt;/posZ&gt;&lt;rotX&gt;-0&lt;/rotX&gt;&lt;rotY&gt;0&lt;/rotY&gt;&lt;rotZ&gt;0&lt;/rotZ&gt;&lt;sclX&gt;854&lt;/sclX&gt;&lt;sclY&gt;480&lt;/sclY&gt;&lt;sclZ&gt;1&lt;/sclZ&gt;&lt;uiAtlasName /&gt;&lt;texturePath&gt;BG/street2&lt;/texturePath&gt;&lt;alpha&gt;1&lt;/alpha&gt;&lt;show&gt;true&lt;/show&gt;&lt;makePixelPerfect&gt;false&lt;/makePixelPerfect&gt;&lt;/SceneNodeData&gt;&lt;SceneNodeData&gt;&lt;name&gt;Sachi&lt;/name&gt;&lt;parentname&gt;ADVScene&lt;/parentname&gt;&lt;nodeType&gt;NODE&lt;/nodeType&gt;&lt;posX&gt;-150&lt;/posX&gt;&lt;posY&gt;0&lt;/posY&gt;&lt;posZ&gt;0&lt;/posZ&gt;&lt;rotX&gt;-0&lt;/rotX&gt;&lt;rotY&gt;0&lt;/rotY&gt;&lt;rotZ&gt;0&lt;/rotZ&gt;&lt;sclX&gt;1.2&lt;/sclX&gt;&lt;sclY&gt;1.2&lt;/sclY&gt;&lt;sclZ&gt;1&lt;/sclZ&gt;&lt;uiAtlasName /&gt;&lt;texturePath /&gt;&lt;alpha&gt;1&lt;/alpha&gt;&lt;show&gt;true&lt;/show&gt;&lt;makePixelPerfect&gt;true&lt;/makePixelPerfect&gt;&lt;/SceneNodeData&gt;&lt;SceneNodeData&gt;&lt;name&gt;sachi_body&lt;/name&gt;&lt;parentname&gt;Sachi&lt;/parentname&gt;&lt;nodeType&gt;LEAF&lt;/nodeType&gt;&lt;posX&gt;0&lt;/posX&gt;&lt;posY&gt;0&lt;/posY&gt;&lt;posZ&gt;0&lt;/posZ&gt;&lt;rotX&gt;-0&lt;/rotX&gt;&lt;rotY&gt;0&lt;/rotY&gt;&lt;rotZ&gt;0&lt;/rotZ&gt;&lt;sclX&gt;300&lt;/sclX&gt;&lt;sclY&gt;400&lt;/sclY&gt;&lt;sclZ&gt;1&lt;/sclZ&gt;&lt;uiAtlasName /&gt;&lt;texturePath&gt;character/sachi/body&lt;/texturePath&gt;&lt;alpha&gt;1&lt;/alpha&gt;&lt;show&gt;true&lt;/show&gt;&lt;makePixelPerfect&gt;true&lt;/makePixelPerfect&gt;&lt;/SceneNodeData&gt;&lt;SceneNodeData&gt;&lt;name&gt;sachi_face&lt;/name&gt;&lt;parentname&gt;Sachi&lt;/parentname&gt;&lt;nodeType&gt;LEAF&lt;/nodeType&gt;&lt;posX&gt;0&lt;/posX&gt;&lt;posY&gt;0&lt;/posY&gt;&lt;posZ&gt;-1&lt;/posZ&gt;&lt;rotX&gt;-0&lt;/rotX&gt;&lt;rotY&gt;0&lt;/rotY&gt;&lt;rotZ&gt;0&lt;/rotZ&gt;&lt;sclX&gt;300&lt;/sclX&gt;&lt;sclY&gt;400&lt;/sclY&gt;&lt;sclZ&gt;1&lt;/sclZ&gt;&lt;uiAtlasName /&gt;&lt;texturePath&gt;character/sachi/normal&lt;/texturePath&gt;&lt;alpha&gt;1&lt;/alpha&gt;&lt;show&gt;true&lt;/show&gt;&lt;makePixelPerfect&gt;true&lt;/makePixelPerfect&gt;&lt;/SceneNodeData&gt;&lt;SceneNodeData&gt;&lt;name&gt;Yoshino&lt;/name&gt;&lt;parentname&gt;ADVScene&lt;/parentname&gt;&lt;nodeType&gt;NODE&lt;/nodeType&gt;&lt;posX&gt;150&lt;/posX&gt;&lt;posY&gt;0&lt;/posY&gt;&lt;posZ&gt;0&lt;/posZ&gt;&lt;rotX&gt;-0&lt;/rotX&gt;&lt;rotY&gt;0&lt;/rotY&gt;&lt;rotZ&gt;0&lt;/rotZ&gt;&lt;sclX&gt;1.2&lt;/sclX&gt;&lt;sclY&gt;1.2&lt;/sclY&gt;&lt;sclZ&gt;1&lt;/sclZ&gt;&lt;uiAtlasName /&gt;&lt;texturePath /&gt;&lt;alpha&gt;1&lt;/alpha&gt;&lt;show&gt;true&lt;/show&gt;&lt;makePixelPerfect&gt;true&lt;/makePixelPerfect&gt;&lt;/SceneNodeData&gt;&lt;SceneNodeData&gt;&lt;name&gt;yoshino_body&lt;/name&gt;&lt;parentname&gt;Yoshino&lt;/parentname&gt;&lt;nodeType&gt;LEAF&lt;/nodeType&gt;&lt;posX&gt;0&lt;/posX&gt;&lt;posY&gt;0&lt;/posY&gt;&lt;posZ&gt;0&lt;/posZ&gt;&lt;rotX&gt;-0&lt;/rotX&gt;&lt;rotY&gt;0&lt;/rotY&gt;&lt;rotZ&gt;0&lt;/rotZ&gt;&lt;sclX&gt;300&lt;/sclX&gt;&lt;sclY&gt;400&lt;/sclY&gt;&lt;sclZ&gt;1&lt;/sclZ&gt;&lt;uiAtlasName /&gt;&lt;texturePath&gt;character/yoshino/body1&lt;/texturePath&gt;&lt;alpha&gt;1&lt;/alpha&gt;&lt;show&gt;true&lt;/show&gt;&lt;makePixelPerfect&gt;true&lt;/makePixelPerfect&gt;&lt;/SceneNodeData&gt;&lt;/m_DataArray&gt;&lt;/SceneData&gt;</m_SceneXmlData><m_BgmName>BGM/komorebi-no-kaze</m_BgmName><m_ScenarioResourceFilePath /><m_Date>2022-08-28 13:32:03</m_Date><m_ScenarioDescription>Oh ! Sachi.</m_ScenarioDescription></ViNoSaveData>